Metadata-Version: 2.1
Name: basic-2d-game-engine
Version: 0.0.1
Summary: A basic 2d game engine
Author: caioslppuo
License-File: license.txt
